eztimer/__init__.py
eztimer/timer.py
py_eztimer-1.0.1.dist-info/METADATA
py_eztimer-1.0.1.dist-info/WHEEL
py_eztimer-1.0.1.dist-info/top_level.txt
py_eztimer-1.0.1.dist-info/RECORD
